{"Type":"gpu","Name":"gpu0","Dimension":"GPUUtilization","Value":0.00,"NodeId":"algo-1","Timestamp":1783653708.501101}
{"Type":"gpu","Name":"gpu0","Dimension":"GPUMemoryUtilization","Value":0.00,"NodeId":"algo-1","Timestamp":1783653708.501101}
{"Type":"memory","Name":"MemoryUsedPercent","Dimension":"","Value":5.11,"NodeId":"algo-1","Timestamp":1783653708.502005}
{"Type":"gpu","Name":"gpu0","Dimension":"GPUUtilization","Value":0.00,"NodeId":"algo-1","Timestamp":1783653709.002233}
{"Type":"gpu","Name":"gpu0","Dimension":"GPUMemoryUtilization","Value":0.00,"NodeId":"algo-1","Timestamp":1783653709.002233}
{"Type":"memory","Name":"MemoryUsedPercent","Dimension":"","Value":5.49,"NodeId":"algo-1","Timestamp":1783653709.002308}
{"Type":"cpu","Name":"cpu0","Dimension":"CPUUtilization","Value":100.00,"NodeId":"algo-1","Timestamp":1783653709.002667}
{"Type":"cpu","Name":"cpu0","Dimension":"I/OWaitPercentage","Value":6.00,"NodeId":"algo-1","Timestamp":1783653709.002667}
{"Type":"cpu","Name":"cpu1","Dimension":"CPUUtilization","Value":97.87,"NodeId":"algo-1","Timestamp":1783653709.002667}
{"Type":"cpu","Name":"cpu1","Dimension":"I/OWaitPercentage","Value":8.51,"NodeId":"algo-1","Timestamp":1783653709.002667}
{"Type":"cpu","Name":"cpu2","Dimension":"CPUUtilization","Value":96.00,"NodeId":"algo-1","Timestamp":1783653709.002667}
{"Type":"cpu","Name":"cpu2","Dimension":"I/OWaitPercentage","Value":2.00,"NodeId":"algo-1","Timestamp":1783653709.002667}
{"Type":"cpu","Name":"cpu3","Dimension":"CPUUtilization","Value":94.12,"NodeId":"algo-1","Timestamp":1783653709.002667}
{"Type":"cpu","Name":"cpu3","Dimension":"I/OWaitPercentage","Value":5.88,"NodeId":"algo-1","Timestamp":1783653709.002667}
{"Type":"i/o","Name":"IOPS","Dimension":"","Value":1244.47,"NodeId":"algo-1","Timestamp":1783653709.002761}
{"Type":"i/o","Name":"ReadThroughputInBytesPerSecond","Dimension":"","Value":0.00,"NodeId":"algo-1","Timestamp":1783653709.002761}
{"Type":"i/o","Name":"WriteThroughputInBytesPerSecond","Dimension":"","Value":163107247.84,"NodeId":"algo-1","Timestamp":1783653709.002761}
{"Type":"network","Name":"ReceiveBytesPerSecond","Dimension":"Algorithm","Value":0.00,"NodeId":"algo-1","Timestamp":1783653709.015076}
{"Type":"network","Name":"TransmitBytesPerSecond","Dimension":"Algorithm","Value":0.00,"NodeId":"algo-1","Timestamp":1783653709.015076}
{"Type":"network","Name":"ReceiveBytesPerSecond","Dimension":"Platform","Value":282789634.57,"NodeId":"algo-1","Timestamp":1783653709.015076}
{"Type":"network","Name":"TransmitBytesPerSecond","Dimension":"Platform","Value":262360.16,"NodeId":"algo-1","Timestamp":1783653709.015076}
{"Type":"gpu","Name":"gpu0","Dimension":"GPUUtilization","Value":0.00,"NodeId":"algo-1","Timestamp":1783653709.501617}
{"Type":"gpu","Name":"gpu0","Dimension":"GPUMemoryUtilization","Value":0.00,"NodeId":"algo-1","Timestamp":1783653709.501617}
{"Type":"cpu","Name":"cpu0","Dimension":"CPUUtilization","Value":100.00,"NodeId":"algo-1","Timestamp":1783653709.501661}
{"Type":"cpu","Name":"cpu0","Dimension":"I/OWaitPercentage","Value":2.08,"NodeId":"algo-1","Timestamp":1783653709.501661}
{"Type":"cpu","Name":"cpu1","Dimension":"CPUUtilization","Value":98.00,"NodeId":"algo-1","Timestamp":1783653709.501661}
{"Type":"cpu","Name":"cpu1","Dimension":"I/OWaitPercentage","Value":4.00,"NodeId":"algo-1","Timestamp":1783653709.501661}
{"Type":"cpu","Name":"cpu2","Dimension":"CPUUtilization","Value":100.00,"NodeId":"algo-1","Timestamp":1783653709.501661}
{"Type":"cpu","Name":"cpu2","Dimension":"I/OWaitPercentage","Value":2.04,"NodeId":"algo-1","Timestamp":1783653709.501661}
{"Type":"cpu","Name":"cpu3","Dimension":"CPUUtilization","Value":98.00,"NodeId":"algo-1","Timestamp":1783653709.501661}
{"Type":"cpu","Name":"cpu3","Dimension":"I/OWaitPercentage","Value":4.00,"NodeId":"algo-1","Timestamp":1783653709.501661}
{"Type":"i/o","Name":"IOPS","Dimension":"","Value":63570.03,"NodeId":"algo-1","Timestamp":1783653709.501974}
{"Type":"i/o","Name":"ReadThroughputInBytesPerSecond","Dimension":"","Value":11585334.25,"NodeId":"algo-1","Timestamp":1783653709.501974}
{"Type":"i/o","Name":"WriteThroughputInBytesPerSecond","Dimension":"","Value":4487969364.84,"NodeId":"algo-1","Timestamp":1783653709.501974}
{"Type":"memory","Name":"MemoryUsedPercent","Dimension":"","Value":5.72,"NodeId":"algo-1","Timestamp":1783653709.502072}
{"Type":"network","Name":"ReceiveBytesPerSecond","Dimension":"Algorithm","Value":0.00,"NodeId":"algo-1","Timestamp":1783653709.506196}
{"Type":"network","Name":"TransmitBytesPerSecond","Dimension":"Algorithm","Value":0.00,"NodeId":"algo-1","Timestamp":1783653709.506196}
{"Type":"network","Name":"ReceiveBytesPerSecond","Dimension":"Platform","Value":255956830.20,"NodeId":"algo-1","Timestamp":1783653709.506196}
{"Type":"network","Name":"TransmitBytesPerSecond","Dimension":"Platform","Value":221166.08,"NodeId":"algo-1","Timestamp":1783653709.506196}
{"Type":"gpu","Name":"gpu0","Dimension":"GPUUtilization","Value":0.00,"NodeId":"algo-1","Timestamp":1783653710.001682}
{"Type":"gpu","Name":"gpu0","Dimension":"GPUMemoryUtilization","Value":0.00,"NodeId":"algo-1","Timestamp":1783653710.001682}
{"Type":"cpu","Name":"cpu0","Dimension":"CPUUtilization","Value":100.00,"NodeId":"algo-1","Timestamp":1783653710.001721}
{"Type":"cpu","Name":"cpu0","Dimension":"I/OWaitPercentage","Value":2.00,"NodeId":"algo-1","Timestamp":1783653710.001721}
{"Type":"cpu","Name":"cpu1","Dimension":"CPUUtilization","Value":100.00,"NodeId":"algo-1","Timestamp":1783653710.001721}
{"Type":"cpu","Name":"cpu1","Dimension":"I/OWaitPercentage","Value":2.00,"NodeId":"algo-1","Timestamp":1783653710.001721}
{"Type":"cpu","Name":"cpu2","Dimension":"CPUUtilization","Value":98.00,"NodeId":"algo-1","Timestamp":1783653710.001721}
{"Type":"cpu","Name":"cpu2","Dimension":"I/OWaitPercentage","Value":2.00,"NodeId":"algo-1","Timestamp":1783653710.001721}
{"Type":"cpu","Name":"cpu3","Dimension":"CPUUtilization","Value":100.00,"NodeId":"algo-1","Timestamp":1783653710.001721}
{"Type":"cpu","Name":"cpu3","Dimension":"I/OWaitPercentage","Value":0.00,"NodeId":"algo-1","Timestamp":1783653710.001721}
{"Type":"i/o","Name":"IOPS","Dimension":"","Value":2493.87,"NodeId":"algo-1","Timestamp":1783653710.002000}
{"Type":"i/o","Name":"ReadThroughputInBytesPerSecond","Dimension":"","Value":0.00,"NodeId":"algo-1","Timestamp":1783653710.002000}
{"Type":"i/o","Name":"WriteThroughputInBytesPerSecond","Dimension":"","Value":326868854.50,"NodeId":"algo-1","Timestamp":1783653710.002000}
{"Type":"memory","Name":"MemoryUsedPercent","Dimension":"","Value":5.92,"NodeId":"algo-1","Timestamp":1783653710.002115}
{"Type":"network","Name":"ReceiveBytesPerSecond","Dimension":"Algorithm","Value":0.00,"NodeId":"algo-1","Timestamp":1783653710.023046}
{"Type":"network","Name":"TransmitBytesPerSecond","Dimension":"Algorithm","Value":0.00,"NodeId":"algo-1","Timestamp":1783653710.023046}
{"Type":"network","Name":"ReceiveBytesPerSecond","Dimension":"Platform","Value":272104560.95,"NodeId":"algo-1","Timestamp":1783653710.023046}
{"Type":"network","Name":"TransmitBytesPerSecond","Dimension":"Platform","Value":358227.89,"NodeId":"algo-1","Timestamp":1783653710.023046}
{"Type":"gpu","Name":"gpu0","Dimension":"GPUUtilization","Value":0.00,"NodeId":"algo-1","Timestamp":1783653710.503395}
{"Type":"gpu","Name":"gpu0","Dimension":"GPUMemoryUtilization","Value":0.00,"NodeId":"algo-1","Timestamp":1783653710.503395}
{"Type":"i/o","Name":"IOPS","Dimension":"","Value":64529.35,"NodeId":"algo-1","Timestamp":1783653710.503461}
{"Type":"i/o","Name":"ReadThroughputInBytesPerSecond","Dimension":"","Value":11533386.28,"NodeId":"algo-1","Timestamp":1783653710.503461}
{"Type":"i/o","Name":"WriteThroughputInBytesPerSecond","Dimension":"","Value":4630946600.33,"NodeId":"algo-1","Timestamp":1783653710.503461}
{"Type":"memory","Name":"MemoryUsedPercent","Dimension":"","Value":6.16,"NodeId":"algo-1","Timestamp":1783653710.504163}
{"Type":"cpu","Name":"cpu0","Dimension":"CPUUtilization","Value":98.00,"NodeId":"algo-1","Timestamp":1783653710.504258}
{"Type":"cpu","Name":"cpu0","Dimension":"I/OWaitPercentage","Value":2.00,"NodeId":"algo-1","Timestamp":1783653710.504258}
{"Type":"cpu","Name":"cpu1","Dimension":"CPUUtilization","Value":100.00,"NodeId":"algo-1","Timestamp":1783653710.504258}
{"Type":"cpu","Name":"cpu1","Dimension":"I/OWaitPercentage","Value":0.00,"NodeId":"algo-1","Timestamp":1783653710.504258}
{"Type":"cpu","Name":"cpu2","Dimension":"CPUUtilization","Value":100.00,"NodeId":"algo-1","Timestamp":1783653710.504258}
{"Type":"cpu","Name":"cpu2","Dimension":"I/OWaitPercentage","Value":2.04,"NodeId":"algo-1","Timestamp":1783653710.504258}
{"Type":"cpu","Name":"cpu3","Dimension":"CPUUtilization","Value":97.96,"NodeId":"algo-1","Timestamp":1783653710.504258}
{"Type":"cpu","Name":"cpu3","Dimension":"I/OWaitPercentage","Value":2.04,"NodeId":"algo-1","Timestamp":1783653710.504258}
{"Type":"network","Name":"ReceiveBytesPerSecond","Dimension":"Algorithm","Value":0.00,"NodeId":"algo-1","Timestamp":1783653710.515184}
{"Type":"network","Name":"TransmitBytesPerSecond","Dimension":"Algorithm","Value":0.00,"NodeId":"algo-1","Timestamp":1783653710.515184}
{"Type":"network","Name":"ReceiveBytesPerSecond","Dimension":"Platform","Value":289983153.65,"NodeId":"algo-1","Timestamp":1783653710.515184}
{"Type":"network","Name":"TransmitBytesPerSecond","Dimension":"Platform","Value":325756.09,"NodeId":"algo-1","Timestamp":1783653710.515184}
{"Type":"gpu","Name":"gpu0","Dimension":"GPUUtilization","Value":0.00,"NodeId":"algo-1","Timestamp":1783653711.002295}
{"Type":"gpu","Name":"gpu0","Dimension":"GPUMemoryUtilization","Value":0.00,"NodeId":"algo-1","Timestamp":1783653711.002295}
{"Type":"cpu","Name":"cpu0","Dimension":"CPUUtilization","Value":100.00,"NodeId":"algo-1","Timestamp":1783653711.002342}
{"Type":"cpu","Name":"cpu0","Dimension":"I/OWaitPercentage","Value":0.00,"NodeId":"algo-1","Timestamp":1783653711.002342}
{"Type":"cpu","Name":"cpu1","Dimension":"CPUUtilization","Value":100.00,"NodeId":"algo-1","Timestamp":1783653711.002342}
{"Type":"cpu","Name":"cpu1","Dimension":"I/OWaitPercentage","Value":4.00,"NodeId":"algo-1","Timestamp":1783653711.002342}
{"Type":"cpu","Name":"cpu2","Dimension":"CPUUtilization","Value":100.00,"NodeId":"algo-1","Timestamp":1783653711.002342}
{"Type":"cpu","Name":"cpu2","Dimension":"I/OWaitPercentage","Value":0.00,"NodeId":"algo-1","Timestamp":1783653711.002342}
{"Type":"cpu","Name":"cpu3","Dimension":"CPUUtilization","Value":97.96,"NodeId":"algo-1","Timestamp":1783653711.002342}
{"Type":"cpu","Name":"cpu3","Dimension":"I/OWaitPercentage","Value":2.04,"NodeId":"algo-1","Timestamp":1783653711.002342}
{"Type":"i/o","Name":"IOPS","Dimension":"","Value":3731.72,"NodeId":"algo-1","Timestamp":1783653711.002427}
{"Type":"i/o","Name":"ReadThroughputInBytesPerSecond","Dimension":"","Value":0.00,"NodeId":"algo-1","Timestamp":1783653711.002427}
{"Type":"i/o","Name":"WriteThroughputInBytesPerSecond","Dimension":"","Value":488656445.45,"NodeId":"algo-1","Timestamp":1783653711.002427}
{"Type":"memory","Name":"MemoryUsedPercent","Dimension":"","Value":6.37,"NodeId":"algo-1","Timestamp":1783653711.002731}
{"Type":"network","Name":"ReceiveBytesPerSecond","Dimension":"Algorithm","Value":0.00,"NodeId":"algo-1","Timestamp":1783653711.015373}
{"Type":"network","Name":"TransmitBytesPerSecond","Dimension":"Algorithm","Value":0.00,"NodeId":"algo-1","Timestamp":1783653711.015373}
{"Type":"network","Name":"ReceiveBytesPerSecond","Dimension":"Platform","Value":268576000.86,"NodeId":"algo-1","Timestamp":1783653711.015373}
{"Type":"network","Name":"TransmitBytesPerSecond","Dimension":"Platform","Value":272193.08,"NodeId":"algo-1","Timestamp":1783653711.015373}
{"Type":"gpu","Name":"gpu0","Dimension":"GPUUtilization","Value":0.00,"NodeId":"algo-1","Timestamp":1783653711.502231}
{"Type":"gpu","Name":"gpu0","Dimension":"GPUMemoryUtilization","Value":0.00,"NodeId":"algo-1","Timestamp":1783653711.502231}
{"Type":"cpu","Name":"cpu1","Dimension":"I/OWaitPercentage","Value":0.00,"NodeId":"algo-1","Timestamp":1783653711.502284}
{"Type":"cpu","Name":"cpu0","Dimension":"I/OWaitPercentage","Value":0.00,"NodeId":"algo-1","Timestamp":1783653711.502284}
{"Type":"cpu","Name":"cpu1","Dimension":"CPUUtilization","Value":98.00,"NodeId":"algo-1","Timestamp":1783653711.502284}
{"Type":"cpu","Name":"cpu0","Dimension":"CPUUtilization","Value":100.00,"NodeId":"algo-1","Timestamp":1783653711.502284}
{"Type":"cpu","Name":"cpu2","Dimension":"CPUUtilization","Value":100.00,"NodeId":"algo-1","Timestamp":1783653711.502284}
{"Type":"cpu","Name":"cpu2","Dimension":"I/OWaitPercentage","Value":0.00,"NodeId":"algo-1","Timestamp":1783653711.502284}
{"Type":"cpu","Name":"cpu3","Dimension":"CPUUtilization","Value":98.04,"NodeId":"algo-1","Timestamp":1783653711.502284}
{"Type":"cpu","Name":"cpu3","Dimension":"I/OWaitPercentage","Value":0.00,"NodeId":"algo-1","Timestamp":1783653711.502284}
{"Type":"i/o","Name":"IOPS","Dimension":"","Value":65968.10,"NodeId":"algo-1","Timestamp":1783653711.502380}
{"Type":"i/o","Name":"ReadThroughputInBytesPerSecond","Dimension":"","Value":11568174.13,"NodeId":"algo-1","Timestamp":1783653711.502380}
{"Type":"i/o","Name":"WriteThroughputInBytesPerSecond","Dimension":"","Value":4807983457.28,"NodeId":"algo-1","Timestamp":1783653711.502380}
{"Type":"memory","Name":"MemoryUsedPercent","Dimension":"","Value":6.68,"NodeId":"algo-1","Timestamp":1783653711.502711}
{"Type":"network","Name":"ReceiveBytesPerSecond","Dimension":"Algorithm","Value":0.00,"NodeId":"algo-1","Timestamp":1783653711.506894}
{"Type":"network","Name":"TransmitBytesPerSecond","Dimension":"Algorithm","Value":0.00,"NodeId":"algo-1","Timestamp":1783653711.506894}
{"Type":"network","Name":"ReceiveBytesPerSecond","Dimension":"Platform","Value":286361850.03,"NodeId":"algo-1","Timestamp":1783653711.506894}
{"Type":"network","Name":"TransmitBytesPerSecond","Dimension":"Platform","Value":328567.93,"NodeId":"algo-1","Timestamp":1783653711.506894}
{"Type":"gpu","Name":"gpu0","Dimension":"GPUUtilization","Value":0.00,"NodeId":"algo-1","Timestamp":1783653712.002400}
{"Type":"gpu","Name":"gpu0","Dimension":"GPUMemoryUtilization","Value":0.00,"NodeId":"algo-1","Timestamp":1783653712.002400}
{"Type":"cpu","Name":"cpu0","Dimension":"CPUUtilization","Value":100.00,"NodeId":"algo-1","Timestamp":1783653712.002450}
{"Type":"cpu","Name":"cpu0","Dimension":"I/OWaitPercentage","Value":0.00,"NodeId":"algo-1","Timestamp":1783653712.002450}
{"Type":"cpu","Name":"cpu1","Dimension":"CPUUtilization","Value":97.96,"NodeId":"algo-1","Timestamp":1783653712.002450}
{"Type":"cpu","Name":"cpu1","Dimension":"I/OWaitPercentage","Value":2.04,"NodeId":"algo-1","Timestamp":1783653712.002450}
{"Type":"cpu","Name":"cpu2","Dimension":"CPUUtilization","Value":98.00,"NodeId":"algo-1","Timestamp":1783653712.002450}
{"Type":"cpu","Name":"cpu2","Dimension":"I/OWaitPercentage","Value":2.00,"NodeId":"algo-1","Timestamp":1783653712.002450}
{"Type":"cpu","Name":"cpu3","Dimension":"CPUUtilization","Value":97.96,"NodeId":"algo-1","Timestamp":1783653712.002450}
{"Type":"cpu","Name":"cpu3","Dimension":"I/OWaitPercentage","Value":0.00,"NodeId":"algo-1","Timestamp":1783653712.002450}
{"Type":"i/o","Name":"IOPS","Dimension":"","Value":4978.22,"NodeId":"algo-1","Timestamp":1783653712.002559}
{"Type":"i/o","Name":"ReadThroughputInBytesPerSecond","Dimension":"","Value":0.00,"NodeId":"algo-1","Timestamp":1783653712.002559}
{"Type":"i/o","Name":"WriteThroughputInBytesPerSecond","Dimension":"","Value":652038428.89,"NodeId":"algo-1","Timestamp":1783653712.002559}
{"Type":"memory","Name":"MemoryUsedPercent","Dimension":"","Value":7.32,"NodeId":"algo-1","Timestamp":1783653712.002900}
{"Type":"network","Name":"ReceiveBytesPerSecond","Dimension":"Algorithm","Value":0.00,"NodeId":"algo-1","Timestamp":1783653712.006741}
{"Type":"network","Name":"TransmitBytesPerSecond","Dimension":"Algorithm","Value":0.00,"NodeId":"algo-1","Timestamp":1783653712.006741}
{"Type":"network","Name":"ReceiveBytesPerSecond","Dimension":"Platform","Value":228567573.27,"NodeId":"algo-1","Timestamp":1783653712.006741}
{"Type":"network","Name":"TransmitBytesPerSecond","Dimension":"Platform","Value":325629.68,"NodeId":"algo-1","Timestamp":1783653712.006741}
{"Type":"gpu","Name":"gpu0","Dimension":"GPUUtilization","Value":0.00,"NodeId":"algo-1","Timestamp":1783653712.502208}
{"Type":"gpu","Name":"gpu0","Dimension":"GPUMemoryUtilization","Value":0.00,"NodeId":"algo-1","Timestamp":1783653712.502208}
{"Type":"cpu","Name":"cpu0","Dimension":"CPUUtilization","Value":95.83,"NodeId":"algo-1","Timestamp":1783653712.502251}
{"Type":"cpu","Name":"cpu0","Dimension":"I/OWaitPercentage","Value":2.08,"NodeId":"algo-1","Timestamp":1783653712.502251}
{"Type":"cpu","Name":"cpu1","Dimension":"CPUUtilization","Value":97.92,"NodeId":"algo-1","Timestamp":1783653712.502251}
{"Type":"cpu","Name":"cpu1","Dimension":"I/OWaitPercentage","Value":4.17,"NodeId":"algo-1","Timestamp":1783653712.502251}
{"Type":"cpu","Name":"cpu2","Dimension":"CPUUtilization","Value":97.96,"NodeId":"algo-1","Timestamp":1783653712.502251}
{"Type":"cpu","Name":"cpu2","Dimension":"I/OWaitPercentage","Value":0.00,"NodeId":"algo-1","Timestamp":1783653712.502251}
{"Type":"cpu","Name":"cpu3","Dimension":"CPUUtilization","Value":95.83,"NodeId":"algo-1","Timestamp":1783653712.502251}
{"Type":"cpu","Name":"cpu3","Dimension":"I/OWaitPercentage","Value":2.08,"NodeId":"algo-1","Timestamp":1783653712.502251}
{"Type":"i/o","Name":"IOPS","Dimension":"","Value":67227.17,"NodeId":"algo-1","Timestamp":1783653712.502342}
{"Type":"i/o","Name":"ReadThroughputInBytesPerSecond","Dimension":"","Value":11572125.40,"NodeId":"algo-1","Timestamp":1783653712.502342}
{"Type":"i/o","Name":"WriteThroughputInBytesPerSecond","Dimension":"","Value":4971701009.52,"NodeId":"algo-1","Timestamp":1783653712.502342}
{"Type":"memory","Name":"MemoryUsedPercent","Dimension":"","Value":8.11,"NodeId":"algo-1","Timestamp":1783653712.502673}
{"Type":"network","Name":"TransmitBytesPerSecond","Dimension":"Platform","Value":348279.21,"NodeId":"algo-1","Timestamp":1783653712.515318}
{"Type":"network","Name":"TransmitBytesPerSecond","Dimension":"Algorithm","Value":0.00,"NodeId":"algo-1","Timestamp":1783653712.515318}
{"Type":"network","Name":"ReceiveBytesPerSecond","Dimension":"Platform","Value":316326508.83,"NodeId":"algo-1","Timestamp":1783653712.515318}
{"Type":"network","Name":"ReceiveBytesPerSecond","Dimension":"Algorithm","Value":0.00,"NodeId":"algo-1","Timestamp":1783653712.515318}
{"Type":"gpu","Name":"gpu0","Dimension":"GPUUtilization","Value":0.00,"NodeId":"algo-1","Timestamp":1783653713.006213}
{"Type":"gpu","Name":"gpu0","Dimension":"GPUMemoryUtilization","Value":0.00,"NodeId":"algo-1","Timestamp":1783653713.006213}
{"Type":"cpu","Name":"cpu0","Dimension":"CPUUtilization","Value":93.88,"NodeId":"algo-1","Timestamp":1783653713.006273}
{"Type":"cpu","Name":"cpu0","Dimension":"I/OWaitPercentage","Value":6.12,"NodeId":"algo-1","Timestamp":1783653713.006273}
{"Type":"cpu","Name":"cpu1","Dimension":"CPUUtilization","Value":98.04,"NodeId":"algo-1","Timestamp":1783653713.006273}
{"Type":"cpu","Name":"cpu1","Dimension":"I/OWaitPercentage","Value":3.92,"NodeId":"algo-1","Timestamp":1783653713.006273}
{"Type":"cpu","Name":"cpu2","Dimension":"CPUUtilization","Value":100.00,"NodeId":"algo-1","Timestamp":1783653713.006273}
{"Type":"cpu","Name":"cpu2","Dimension":"I/OWaitPercentage","Value":4.08,"NodeId":"algo-1","Timestamp":1783653713.006273}
{"Type":"cpu","Name":"cpu3","Dimension":"CPUUtilization","Value":98.00,"NodeId":"algo-1","Timestamp":1783653713.006273}
{"Type":"cpu","Name":"cpu3","Dimension":"I/OWaitPercentage","Value":0.00,"NodeId":"algo-1","Timestamp":1783653713.006273}
{"Type":"i/o","Name":"IOPS","Dimension":"","Value":6177.82,"NodeId":"algo-1","Timestamp":1783653713.006403}
{"Type":"i/o","Name":"ReadThroughputInBytesPerSecond","Dimension":"","Value":0.00,"NodeId":"algo-1","Timestamp":1783653713.006403}
{"Type":"i/o","Name":"WriteThroughputInBytesPerSecond","Dimension":"","Value":809268428.28,"NodeId":"algo-1","Timestamp":1783653713.006403}
{"Type":"memory","Name":"MemoryUsedPercent","Dimension":"","Value":8.87,"NodeId":"algo-1","Timestamp":1783653713.006740}
{"Type":"network","Name":"ReceiveBytesPerSecond","Dimension":"Algorithm","Value":0.00,"NodeId":"algo-1","Timestamp":1783653713.010103}
{"Type":"network","Name":"TransmitBytesPerSecond","Dimension":"Algorithm","Value":0.00,"NodeId":"algo-1","Timestamp":1783653713.010103}
{"Type":"network","Name":"ReceiveBytesPerSecond","Dimension":"Platform","Value":282065900.11,"NodeId":"algo-1","Timestamp":1783653713.010103}
{"Type":"network","Name":"TransmitBytesPerSecond","Dimension":"Platform","Value":342140.64,"NodeId":"algo-1","Timestamp":1783653713.010103}
{"Type":"gpu","Name":"gpu0","Dimension":"GPUUtilization","Value":0.00,"NodeId":"algo-1","Timestamp":1783653713.501901}
{"Type":"gpu","Name":"gpu0","Dimension":"GPUMemoryUtilization","Value":0.00,"NodeId":"algo-1","Timestamp":1783653713.501901}
{"Type":"cpu","Name":"cpu1","Dimension":"I/OWaitPercentage","Value":6.12,"NodeId":"algo-1","Timestamp":1783653713.501942}
{"Type":"cpu","Name":"cpu0","Dimension":"I/OWaitPercentage","Value":4.26,"NodeId":"algo-1","Timestamp":1783653713.501942}
{"Type":"cpu","Name":"cpu1","Dimension":"CPUUtilization","Value":95.92,"NodeId":"algo-1","Timestamp":1783653713.501942}
{"Type":"cpu","Name":"cpu0","Dimension":"CPUUtilization","Value":97.87,"NodeId":"algo-1","Timestamp":1783653713.501942}
{"Type":"cpu","Name":"cpu2","Dimension":"CPUUtilization","Value":98.00,"NodeId":"algo-1","Timestamp":1783653713.501942}
{"Type":"cpu","Name":"cpu2","Dimension":"I/OWaitPercentage","Value":4.00,"NodeId":"algo-1","Timestamp":1783653713.501942}
{"Type":"cpu","Name":"cpu3","Dimension":"CPUUtilization","Value":96.00,"NodeId":"algo-1","Timestamp":1783653713.501942}
{"Type":"cpu","Name":"cpu3","Dimension":"I/OWaitPercentage","Value":4.00,"NodeId":"algo-1","Timestamp":1783653713.501942}
{"Type":"i/o","Name":"IOPS","Dimension":"","Value":68993.08,"NodeId":"algo-1","Timestamp":1783653713.502207}
{"Type":"i/o","Name":"ReadThroughputInBytesPerSecond","Dimension":"","Value":11665011.80,"NodeId":"algo-1","Timestamp":1783653713.502207}
{"Type":"i/o","Name":"WriteThroughputInBytesPerSecond","Dimension":"","Value":5172340170.92,"NodeId":"algo-1","Timestamp":1783653713.502207}
{"Type":"memory","Name":"MemoryUsedPercent","Dimension":"","Value":9.72,"NodeId":"algo-1","Timestamp":1783653713.502788}
{"Type":"network","Name":"TransmitBytesPerSecond","Dimension":"Platform","Value":282388.39,"NodeId":"algo-1","Timestamp":1783653713.512344}
{"Type":"network","Name":"TransmitBytesPerSecond","Dimension":"Algorithm","Value":0.00,"NodeId":"algo-1","Timestamp":1783653713.512344}
{"Type":"network","Name":"ReceiveBytesPerSecond","Dimension":"Platform","Value":304015354.28,"NodeId":"algo-1","Timestamp":1783653713.512344}
{"Type":"network","Name":"ReceiveBytesPerSecond","Dimension":"Algorithm","Value":0.00,"NodeId":"algo-1","Timestamp":1783653713.512344}
{"Type":"gpu","Name":"gpu0","Dimension":"GPUUtilization","Value":0.00,"NodeId":"algo-1","Timestamp":1783653714.002219}
{"Type":"gpu","Name":"gpu0","Dimension":"GPUMemoryUtilization","Value":0.00,"NodeId":"algo-1","Timestamp":1783653714.002219}
{"Type":"cpu","Name":"cpu1","Dimension":"I/OWaitPercentage","Value":0.00,"NodeId":"algo-1","Timestamp":1783653714.002300}
{"Type":"cpu","Name":"cpu0","Dimension":"I/OWaitPercentage","Value":11.76,"NodeId":"algo-1","Timestamp":1783653714.002300}
{"Type":"cpu","Name":"cpu1","Dimension":"CPUUtilization","Value":98.00,"NodeId":"algo-1","Timestamp":1783653714.002300}
{"Type":"cpu","Name":"cpu0","Dimension":"CPUUtilization","Value":98.04,"NodeId":"algo-1","Timestamp":1783653714.002300}
{"Type":"cpu","Name":"cpu2","Dimension":"CPUUtilization","Value":94.00,"NodeId":"algo-1","Timestamp":1783653714.002300}
{"Type":"cpu","Name":"cpu2","Dimension":"I/OWaitPercentage","Value":4.00,"NodeId":"algo-1","Timestamp":1783653714.002300}
{"Type":"cpu","Name":"cpu3","Dimension":"CPUUtilization","Value":96.08,"NodeId":"algo-1","Timestamp":1783653714.002300}
{"Type":"cpu","Name":"cpu3","Dimension":"I/OWaitPercentage","Value":11.76,"NodeId":"algo-1","Timestamp":1783653714.002300}
{"Type":"i/o","Name":"IOPS","Dimension":"","Value":7479.28,"NodeId":"algo-1","Timestamp":1783653714.002389}
{"Type":"i/o","Name":"ReadThroughputInBytesPerSecond","Dimension":"","Value":0.00,"NodeId":"algo-1","Timestamp":1783653714.002389}
{"Type":"i/o","Name":"WriteThroughputInBytesPerSecond","Dimension":"","Value":979848605.64,"NodeId":"algo-1","Timestamp":1783653714.002389}
{"Type":"memory","Name":"MemoryUsedPercent","Dimension":"","Value":9.97,"NodeId":"algo-1","Timestamp":1783653714.002671}
{"Type":"network","Name":"TransmitBytesPerSecond","Dimension":"Algorithm","Value":0.00,"NodeId":"algo-1","Timestamp":1783653714.006747}
{"Type":"network","Name":"ReceiveBytesPerSecond","Dimension":"Algorithm","Value":0.00,"NodeId":"algo-1","Timestamp":1783653714.006747}
{"Type":"network","Name":"ReceiveBytesPerSecond","Dimension":"Platform","Value":267086322.13,"NodeId":"algo-1","Timestamp":1783653714.006747}
{"Type":"network","Name":"TransmitBytesPerSecond","Dimension":"Platform","Value":247296.17,"NodeId":"algo-1","Timestamp":1783653714.006747}
{"Type":"gpu","Name":"gpu0","Dimension":"GPUUtilization","Value":0.00,"NodeId":"algo-1","Timestamp":1783653714.506367}
{"Type":"gpu","Name":"gpu0","Dimension":"GPUMemoryUtilization","Value":0.00,"NodeId":"algo-1","Timestamp":1783653714.506367}
{"Type":"cpu","Name":"cpu0","Dimension":"CPUUtilization","Value":97.96,"NodeId":"algo-1","Timestamp":1783653714.506407}
{"Type":"cpu","Name":"cpu0","Dimension":"I/OWaitPercentage","Value":2.04,"NodeId":"algo-1","Timestamp":1783653714.506407}
{"Type":"cpu","Name":"cpu1","Dimension":"CPUUtilization","Value":100.00,"NodeId":"algo-1","Timestamp":1783653714.506407}
{"Type":"cpu","Name":"cpu1","Dimension":"I/OWaitPercentage","Value":6.12,"NodeId":"algo-1","Timestamp":1783653714.506407}
{"Type":"cpu","Name":"cpu2","Dimension":"CPUUtilization","Value":100.00,"NodeId":"algo-1","Timestamp":1783653714.506407}
{"Type":"cpu","Name":"cpu2","Dimension":"I/OWaitPercentage","Value":2.00,"NodeId":"algo-1","Timestamp":1783653714.506407}
{"Type":"cpu","Name":"cpu3","Dimension":"CPUUtilization","Value":100.00,"NodeId":"algo-1","Timestamp":1783653714.506407}
{"Type":"cpu","Name":"cpu3","Dimension":"I/OWaitPercentage","Value":11.36,"NodeId":"algo-1","Timestamp":1783653714.506407}
{"Type":"i/o","Name":"IOPS","Dimension":"","Value":69045.01,"NodeId":"algo-1","Timestamp":1783653714.506813}
{"Type":"i/o","Name":"ReadThroughputInBytesPerSecond","Dimension":"","Value":11465642.88,"NodeId":"algo-1","Timestamp":1783653714.506813}
{"Type":"i/o","Name":"WriteThroughputInBytesPerSecond","Dimension":"","Value":5245294101.27,"NodeId":"algo-1","Timestamp":1783653714.506813}
{"Type":"memory","Name":"MemoryUsedPercent","Dimension":"","Value":10.05,"NodeId":"algo-1","Timestamp":1783653714.506947}
{"Type":"network","Name":"TransmitBytesPerSecond","Dimension":"Platform","Value":278460.40,"NodeId":"algo-1","Timestamp":1783653714.514679}
{"Type":"network","Name":"TransmitBytesPerSecond","Dimension":"Algorithm","Value":0.00,"NodeId":"algo-1","Timestamp":1783653714.514679}
{"Type":"network","Name":"ReceiveBytesPerSecond","Dimension":"Platform","Value":295355502.36,"NodeId":"algo-1","Timestamp":1783653714.514679}
{"Type":"network","Name":"ReceiveBytesPerSecond","Dimension":"Algorithm","Value":0.00,"NodeId":"algo-1","Timestamp":1783653714.514679}
{"Type":"gpu","Name":"gpu0","Dimension":"GPUUtilization","Value":0.00,"NodeId":"algo-1","Timestamp":1783653715.002252}
{"Type":"gpu","Name":"gpu0","Dimension":"GPUMemoryUtilization","Value":0.00,"NodeId":"algo-1","Timestamp":1783653715.002252}
{"Type":"cpu","Name":"cpu1","Dimension":"CPUUtilization","Value":97.96,"NodeId":"algo-1","Timestamp":1783653715.002293}
{"Type":"cpu","Name":"cpu3","Dimension":"CPUUtilization","Value":95.74,"NodeId":"algo-1","Timestamp":1783653715.002293}
{"Type":"cpu","Name":"cpu3","Dimension":"I/OWaitPercentage","Value":6.38,"NodeId":"algo-1","Timestamp":1783653715.002293}
{"Type":"cpu","Name":"cpu2","Dimension":"I/OWaitPercentage","Value":10.00,"NodeId":"algo-1","Timestamp":1783653715.002293}
{"Type":"cpu","Name":"cpu0","Dimension":"I/OWaitPercentage","Value":14.89,"NodeId":"algo-1","Timestamp":1783653715.002293}
{"Type":"cpu","Name":"cpu0","Dimension":"CPUUtilization","Value":93.62,"NodeId":"algo-1","Timestamp":1783653715.002293}
{"Type":"cpu","Name":"cpu1","Dimension":"I/OWaitPercentage","Value":4.08,"NodeId":"algo-1","Timestamp":1783653715.002293}
{"Type":"cpu","Name":"cpu2","Dimension":"CPUUtilization","Value":94.00,"NodeId":"algo-1","Timestamp":1783653715.002293}
{"Type":"i/o","Name":"WriteThroughputInBytesPerSecond","Dimension":"","Value":1152971543.73,"NodeId":"algo-1","Timestamp":1783653715.002601}
{"Type":"i/o","Name":"IOPS","Dimension":"","Value":8800.13,"NodeId":"algo-1","Timestamp":1783653715.002601}
{"Type":"i/o","Name":"ReadThroughputInBytesPerSecond","Dimension":"","Value":0.00,"NodeId":"algo-1","Timestamp":1783653715.002601}
{"Type":"memory","Name":"MemoryUsedPercent","Dimension":"","Value":10.05,"NodeId":"algo-1","Timestamp":1783653715.002737}
{"Type":"network","Name":"ReceiveBytesPerSecond","Dimension":"Algorithm","Value":0.00,"NodeId":"algo-1","Timestamp":1783653715.009796}
{"Type":"network","Name":"TransmitBytesPerSecond","Dimension":"Algorithm","Value":0.00,"NodeId":"algo-1","Timestamp":1783653715.009796}
{"Type":"network","Name":"ReceiveBytesPerSecond","Dimension":"Platform","Value":272300561.17,"NodeId":"algo-1","Timestamp":1783653715.009796}
{"Type":"network","Name":"TransmitBytesPerSecond","Dimension":"Platform","Value":284692.20,"NodeId":"algo-1","Timestamp":1783653715.009796}
{"Type":"gpu","Name":"gpu0","Dimension":"GPUUtilization","Value":0.00,"NodeId":"algo-1","Timestamp":1783653715.502215}
{"Type":"gpu","Name":"gpu0","Dimension":"GPUMemoryUtilization","Value":0.00,"NodeId":"algo-1","Timestamp":1783653715.502215}
{"Type":"cpu","Name":"cpu3","Dimension":"I/OWaitPercentage","Value":21.74,"NodeId":"algo-1","Timestamp":1783653715.502236}
{"Type":"cpu","Name":"cpu0","Dimension":"I/OWaitPercentage","Value":0.00,"NodeId":"algo-1","Timestamp":1783653715.502236}
{"Type":"cpu","Name":"cpu1","Dimension":"CPUUtilization","Value":97.87,"NodeId":"algo-1","Timestamp":1783653715.502236}
{"Type":"cpu","Name":"cpu1","Dimension":"I/OWaitPercentage","Value":21.28,"NodeId":"algo-1","Timestamp":1783653715.502236}
{"Type":"cpu","Name":"cpu2","Dimension":"CPUUtilization","Value":100.00,"NodeId":"algo-1","Timestamp":1783653715.502236}
{"Type":"cpu","Name":"cpu2","Dimension":"I/OWaitPercentage","Value":0.00,"NodeId":"algo-1","Timestamp":1783653715.502236}
{"Type":"cpu","Name":"cpu3","Dimension":"CPUUtilization","Value":95.65,"NodeId":"algo-1","Timestamp":1783653715.502236}
{"Type":"cpu","Name":"cpu0","Dimension":"CPUUtilization","Value":100.00,"NodeId":"algo-1","Timestamp":1783653715.502236}
{"Type":"memory","Name":"MemoryUsedPercent","Dimension":"","Value":10.08,"NodeId":"algo-1","Timestamp":1783653715.502367}
{"Type":"i/o","Name":"IOPS","Dimension":"","Value":70917.44,"NodeId":"algo-1","Timestamp":1783653715.502450}
{"Type":"i/o","Name":"ReadThroughputInBytesPerSecond","Dimension":"","Value":11570601.96,"NodeId":"algo-1","Timestamp":1783653715.502450}
{"Type":"i/o","Name":"WriteThroughputInBytesPerSecond","Dimension":"","Value":5455889139.81,"NodeId":"algo-1","Timestamp":1783653715.502450}
{"Type":"network","Name":"ReceiveBytesPerSecond","Dimension":"Algorithm","Value":0.00,"NodeId":"algo-1","Timestamp":1783653715.515840}
{"Type":"network","Name":"TransmitBytesPerSecond","Dimension":"Algorithm","Value":0.00,"NodeId":"algo-1","Timestamp":1783653715.515840}
{"Type":"network","Name":"ReceiveBytesPerSecond","Dimension":"Platform","Value":319113149.23,"NodeId":"algo-1","Timestamp":1783653715.515840}
{"Type":"network","Name":"TransmitBytesPerSecond","Dimension":"Platform","Value":307305.49,"NodeId":"algo-1","Timestamp":1783653715.515840}
{"Type":"gpu","Name":"gpu0","Dimension":"GPUUtilization","Value":0.00,"NodeId":"algo-1","Timestamp":1783653716.002209}
{"Type":"gpu","Name":"gpu0","Dimension":"GPUMemoryUtilization","Value":0.00,"NodeId":"algo-1","Timestamp":1783653716.002209}
{"Type":"cpu","Name":"cpu0","Dimension":"CPUUtilization","Value":100.00,"NodeId":"algo-1","Timestamp":1783653716.002256}
{"Type":"cpu","Name":"cpu0","Dimension":"I/OWaitPercentage","Value":0.00,"NodeId":"algo-1","Timestamp":1783653716.002256}
{"Type":"cpu","Name":"cpu1","Dimension":"CPUUtilization","Value":100.00,"NodeId":"algo-1","Timestamp":1783653716.002256}
{"Type":"cpu","Name":"cpu1","Dimension":"I/OWaitPercentage","Value":8.16,"NodeId":"algo-1","Timestamp":1783653716.002256}
{"Type":"cpu","Name":"cpu2","Dimension":"CPUUtilization","Value":100.00,"NodeId":"algo-1","Timestamp":1783653716.002256}
{"Type":"cpu","Name":"cpu2","Dimension":"I/OWaitPercentage","Value":0.00,"NodeId":"algo-1","Timestamp":1783653716.002256}
{"Type":"cpu","Name":"cpu3","Dimension":"CPUUtilization","Value":97.96,"NodeId":"algo-1","Timestamp":1783653716.002256}
{"Type":"cpu","Name":"cpu3","Dimension":"I/OWaitPercentage","Value":4.08,"NodeId":"algo-1","Timestamp":1783653716.002256}
{"Type":"i/o","Name":"IOPS","Dimension":"","Value":10012.01,"NodeId":"algo-1","Timestamp":1783653716.002350}
{"Type":"i/o","Name":"ReadThroughputInBytesPerSecond","Dimension":"","Value":0.00,"NodeId":"algo-1","Timestamp":1783653716.002350}
{"Type":"i/o","Name":"WriteThroughputInBytesPerSecond","Dimension":"","Value":1305107712.02,"NodeId":"algo-1","Timestamp":1783653716.002350}
{"Type":"memory","Name":"MemoryUsedPercent","Dimension":"","Value":10.25,"NodeId":"algo-1","Timestamp":1783653716.002726}
{"Type":"network","Name":"ReceiveBytesPerSecond","Dimension":"Algorithm","Value":0.00,"NodeId":"algo-1","Timestamp":1783653716.006929}
{"Type":"network","Name":"TransmitBytesPerSecond","Dimension":"Algorithm","Value":0.00,"NodeId":"algo-1","Timestamp":1783653716.006929}
{"Type":"network","Name":"ReceiveBytesPerSecond","Dimension":"Platform","Value":294362978.47,"NodeId":"algo-1","Timestamp":1783653716.006929}
{"Type":"network","Name":"TransmitBytesPerSecond","Dimension":"Platform","Value":267908.48,"NodeId":"algo-1","Timestamp":1783653716.006929}
{"Type":"gpu","Name":"gpu0","Dimension":"GPUUtilization","Value":0.00,"NodeId":"algo-1","Timestamp":1783653716.501192}
{"Type":"gpu","Name":"gpu0","Dimension":"GPUMemoryUtilization","Value":0.00,"NodeId":"algo-1","Timestamp":1783653716.501192}
{"Type":"cpu","Name":"cpu0","Dimension":"CPUUtilization","Value":100.00,"NodeId":"algo-1","Timestamp":1783653716.501231}
{"Type":"cpu","Name":"cpu0","Dimension":"I/OWaitPercentage","Value":0.00,"NodeId":"algo-1","Timestamp":1783653716.501231}
{"Type":"cpu","Name":"cpu1","Dimension":"CPUUtilization","Value":97.92,"NodeId":"algo-1","Timestamp":1783653716.501231}
{"Type":"cpu","Name":"cpu1","Dimension":"I/OWaitPercentage","Value":8.33,"NodeId":"algo-1","Timestamp":1783653716.501231}
{"Type":"cpu","Name":"cpu2","Dimension":"CPUUtilization","Value":97.96,"NodeId":"algo-1","Timestamp":1783653716.501231}
{"Type":"cpu","Name":"cpu2","Dimension":"I/OWaitPercentage","Value":2.04,"NodeId":"algo-1","Timestamp":1783653716.501231}
{"Type":"cpu","Name":"cpu3","Dimension":"CPUUtilization","Value":97.96,"NodeId":"algo-1","Timestamp":1783653716.501231}
{"Type":"cpu","Name":"cpu3","Dimension":"I/OWaitPercentage","Value":10.20,"NodeId":"algo-1","Timestamp":1783653716.501231}
{"Type":"i/o","Name":"IOPS","Dimension":"","Value":72285.73,"NodeId":"algo-1","Timestamp":1783653716.501342}
{"Type":"i/o","Name":"ReadThroughputInBytesPerSecond","Dimension":"","Value":11590471.17,"NodeId":"algo-1","Timestamp":1783653716.501342}
{"Type":"i/o","Name":"WriteThroughputInBytesPerSecond","Dimension":"","Value":5628641032.28,"NodeId":"algo-1","Timestamp":1783653716.501342}
{"Type":"memory","Name":"MemoryUsedPercent","Dimension":"","Value":10.32,"NodeId":"algo-1","Timestamp":1783653716.501693}
{"Type":"network","Name":"ReceiveBytesPerSecond","Dimension":"Algorithm","Value":0.00,"NodeId":"algo-1","Timestamp":1783653716.510711}
{"Type":"network","Name":"TransmitBytesPerSecond","Dimension":"Algorithm","Value":0.00,"NodeId":"algo-1","Timestamp":1783653716.510711}
{"Type":"network","Name":"ReceiveBytesPerSecond","Dimension":"Platform","Value":284139568.52,"NodeId":"algo-1","Timestamp":1783653716.510711}
{"Type":"network","Name":"TransmitBytesPerSecond","Dimension":"Platform","Value":263947.61,"NodeId":"algo-1","Timestamp":1783653716.510711}
{"Type":"gpu","Name":"gpu0","Dimension":"GPUUtilization","Value":0.00,"NodeId":"algo-1","Timestamp":1783653717.001218}
{"Type":"gpu","Name":"gpu0","Dimension":"GPUMemoryUtilization","Value":0.00,"NodeId":"algo-1","Timestamp":1783653717.001218}
{"Type":"i/o","Name":"IOPS","Dimension":"","Value":11252.69,"NodeId":"algo-1","Timestamp":1783653717.001223}
{"Type":"i/o","Name":"ReadThroughputInBytesPerSecond","Dimension":"","Value":0.00,"NodeId":"algo-1","Timestamp":1783653717.001223}
{"Type":"i/o","Name":"WriteThroughputInBytesPerSecond","Dimension":"","Value":1467726249.07,"NodeId":"algo-1","Timestamp":1783653717.001223}
{"Type":"cpu","Name":"cpu1","Dimension":"CPUUtilization","Value":100.00,"NodeId":"algo-1","Timestamp":1783653717.001321}
{"Type":"cpu","Name":"cpu0","Dimension":"I/OWaitPercentage","Value":0.00,"NodeId":"algo-1","Timestamp":1783653717.001321}
{"Type":"cpu","Name":"cpu0","Dimension":"CPUUtilization","Value":100.00,"NodeId":"algo-1","Timestamp":1783653717.001321}
{"Type":"cpu","Name":"cpu1","Dimension":"I/OWaitPercentage","Value":8.33,"NodeId":"algo-1","Timestamp":1783653717.001321}
{"Type":"cpu","Name":"cpu2","Dimension":"CPUUtilization","Value":100.00,"NodeId":"algo-1","Timestamp":1783653717.001321}
{"Type":"cpu","Name":"cpu2","Dimension":"I/OWaitPercentage","Value":0.00,"NodeId":"algo-1","Timestamp":1783653717.001321}
{"Type":"cpu","Name":"cpu3","Dimension":"CPUUtilization","Value":98.00,"NodeId":"algo-1","Timestamp":1783653717.001321}
{"Type":"cpu","Name":"cpu3","Dimension":"I/OWaitPercentage","Value":12.00,"NodeId":"algo-1","Timestamp":1783653717.001321}
{"Type":"memory","Name":"MemoryUsedPercent","Dimension":"","Value":10.32,"NodeId":"algo-1","Timestamp":1783653717.001397}
{"Type":"network","Name":"ReceiveBytesPerSecond","Dimension":"Algorithm","Value":0.00,"NodeId":"algo-1","Timestamp":1783653717.013663}
{"Type":"network","Name":"TransmitBytesPerSecond","Dimension":"Algorithm","Value":0.00,"NodeId":"algo-1","Timestamp":1783653717.013663}
{"Type":"network","Name":"ReceiveBytesPerSecond","Dimension":"Platform","Value":319745420.29,"NodeId":"algo-1","Timestamp":1783653717.013663}
{"Type":"network","Name":"TransmitBytesPerSecond","Dimension":"Platform","Value":314749.81,"NodeId":"algo-1","Timestamp":1783653717.013663}
{"Type":"gpu","Name":"gpu0","Dimension":"GPUUtilization","Value":0.00,"NodeId":"algo-1","Timestamp":1783653717.502218}
{"Type":"gpu","Name":"gpu0","Dimension":"GPUMemoryUtilization","Value":0.00,"NodeId":"algo-1","Timestamp":1783653717.502218}
{"Type":"i/o","Name":"IOPS","Dimension":"","Value":73215.45,"NodeId":"algo-1","Timestamp":1783653717.502278}
{"Type":"i/o","Name":"ReadThroughputInBytesPerSecond","Dimension":"","Value":11542737.76,"NodeId":"algo-1","Timestamp":1783653717.502278}
{"Type":"i/o","Name":"WriteThroughputInBytesPerSecond","Dimension":"","Value":5766331196.46,"NodeId":"algo-1","Timestamp":1783653717.502278}
{"Type":"cpu","Name":"cpu0","Dimension":"CPUUtilization","Value":84.62,"NodeId":"algo-1","Timestamp":1783653717.502318}
{"Type":"cpu","Name":"cpu0","Dimension":"I/OWaitPercentage","Value":15.38,"NodeId":"algo-1","Timestamp":1783653717.502318}
{"Type":"cpu","Name":"cpu1","Dimension":"CPUUtilization","Value":91.67,"NodeId":"algo-1","Timestamp":1783653717.502318}
{"Type":"cpu","Name":"cpu1","Dimension":"I/OWaitPercentage","Value":22.92,"NodeId":"algo-1","Timestamp":1783653717.502318}
{"Type":"cpu","Name":"cpu2","Dimension":"CPUUtilization","Value":91.67,"NodeId":"algo-1","Timestamp":1783653717.502318}
{"Type":"cpu","Name":"cpu2","Dimension":"I/OWaitPercentage","Value":18.75,"NodeId":"algo-1","Timestamp":1783653717.502318}
{"Type":"cpu","Name":"cpu3","Dimension":"CPUUtilization","Value":93.18,"NodeId":"algo-1","Timestamp":1783653717.502318}
{"Type":"cpu","Name":"cpu3","Dimension":"I/OWaitPercentage","Value":25.00,"NodeId":"algo-1","Timestamp":1783653717.502318}
{"Type":"memory","Name":"MemoryUsedPercent","Dimension":"","Value":10.37,"NodeId":"algo-1","Timestamp":1783653717.502404}
{"Type":"network","Name":"ReceiveBytesPerSecond","Dimension":"Algorithm","Value":0.00,"NodeId":"algo-1","Timestamp":1783653717.506125}
{"Type":"network","Name":"TransmitBytesPerSecond","Dimension":"Algorithm","Value":0.00,"NodeId":"algo-1","Timestamp":1783653717.506125}
{"Type":"network","Name":"ReceiveBytesPerSecond","Dimension":"Platform","Value":317483391.77,"NodeId":"algo-1","Timestamp":1783653717.506125}
{"Type":"network","Name":"TransmitBytesPerSecond","Dimension":"Platform","Value":389962.77,"NodeId":"algo-1","Timestamp":1783653717.506125}
{"Type":"i/o","Name":"IOPS","Dimension":"","Value":12509.97,"NodeId":"algo-1","Timestamp":1783653718.001720}
{"Type":"i/o","Name":"ReadThroughputInBytesPerSecond","Dimension":"","Value":0.00,"NodeId":"algo-1","Timestamp":1783653718.001720}
{"Type":"i/o","Name":"WriteThroughputInBytesPerSecond","Dimension":"","Value":1632506241.63,"NodeId":"algo-1","Timestamp":1783653718.001720}
{"Type":"memory","Name":"MemoryUsedPercent","Dimension":"","Value":10.35,"NodeId":"algo-1","Timestamp":1783653718.001945}
{"Type":"cpu","Name":"cpu0","Dimension":"CPUUtilization","Value":71.74,"NodeId":"algo-1","Timestamp":1783653718.002077}
{"Type":"cpu","Name":"cpu0","Dimension":"I/OWaitPercentage","Value":21.74,"NodeId":"algo-1","Timestamp":1783653718.002077}
{"Type":"cpu","Name":"cpu1","Dimension":"CPUUtilization","Value":85.42,"NodeId":"algo-1","Timestamp":1783653718.002077}
{"Type":"cpu","Name":"cpu1","Dimension":"I/OWaitPercentage","Value":27.08,"NodeId":"algo-1","Timestamp":1783653718.002077}
{"Type":"cpu","Name":"cpu2","Dimension":"CPUUtilization","Value":91.84,"NodeId":"algo-1","Timestamp":1783653718.002077}
{"Type":"cpu","Name":"cpu2","Dimension":"I/OWaitPercentage","Value":34.69,"NodeId":"algo-1","Timestamp":1783653718.002077}
{"Type":"cpu","Name":"cpu3","Dimension":"CPUUtilization","Value":80.39,"NodeId":"algo-1","Timestamp":1783653718.002077}
{"Type":"cpu","Name":"cpu3","Dimension":"I/OWaitPercentage","Value":23.53,"NodeId":"algo-1","Timestamp":1783653718.002077}
{"Type":"gpu","Name":"gpu0","Dimension":"GPUUtilization","Value":0.00,"NodeId":"algo-1","Timestamp":1783653718.002124}
{"Type":"gpu","Name":"gpu0","Dimension":"GPUMemoryUtilization","Value":0.00,"NodeId":"algo-1","Timestamp":1783653718.002124}
{"Type":"network","Name":"ReceiveBytesPerSecond","Dimension":"Algorithm","Value":0.00,"NodeId":"algo-1","Timestamp":1783653718.005690}
{"Type":"network","Name":"TransmitBytesPerSecond","Dimension":"Algorithm","Value":0.00,"NodeId":"algo-1","Timestamp":1783653718.005690}
{"Type":"network","Name":"ReceiveBytesPerSecond","Dimension":"Platform","Value":311368511.54,"NodeId":"algo-1","Timestamp":1783653718.005690}
{"Type":"network","Name":"TransmitBytesPerSecond","Dimension":"Platform","Value":371076.92,"NodeId":"algo-1","Timestamp":1783653718.005690}
{"Type":"gpu","Name":"gpu0","Dimension":"GPUUtilization","Value":0.00,"NodeId":"algo-1","Timestamp":1783653718.501838}
{"Type":"gpu","Name":"gpu0","Dimension":"GPUMemoryUtilization","Value":0.00,"NodeId":"algo-1","Timestamp":1783653718.501838}
{"Type":"i/o","Name":"IOPS","Dimension":"","Value":74596.22,"NodeId":"algo-1","Timestamp":1783653718.501852}
{"Type":"i/o","Name":"ReadThroughputInBytesPerSecond","Dimension":"","Value":11564038.13,"NodeId":"algo-1","Timestamp":1783653718.501852}
{"Type":"i/o","Name":"WriteThroughputInBytesPerSecond","Dimension":"","Value":5940244505.70,"NodeId":"algo-1","Timestamp":1783653718.501852}
{"Type":"cpu","Name":"cpu0","Dimension":"CPUUtilization","Value":89.13,"NodeId":"algo-1","Timestamp":1783653718.501884}
{"Type":"cpu","Name":"cpu0","Dimension":"I/OWaitPercentage","Value":58.70,"NodeId":"algo-1","Timestamp":1783653718.501884}
{"Type":"cpu","Name":"cpu1","Dimension":"CPUUtilization","Value":75.00,"NodeId":"algo-1","Timestamp":1783653718.501884}
{"Type":"cpu","Name":"cpu1","Dimension":"I/OWaitPercentage","Value":33.33,"NodeId":"algo-1","Timestamp":1783653718.501884}
{"Type":"cpu","Name":"cpu2","Dimension":"CPUUtilization","Value":75.00,"NodeId":"algo-1","Timestamp":1783653718.501884}
{"Type":"cpu","Name":"cpu2","Dimension":"I/OWaitPercentage","Value":33.33,"NodeId":"algo-1","Timestamp":1783653718.501884}
{"Type":"cpu","Name":"cpu3","Dimension":"CPUUtilization","Value":70.21,"NodeId":"algo-1","Timestamp":1783653718.501884}
{"Type":"cpu","Name":"cpu3","Dimension":"I/OWaitPercentage","Value":25.53,"NodeId":"algo-1","Timestamp":1783653718.501884}
{"Type":"memory","Name":"MemoryUsedPercent","Dimension":"","Value":10.38,"NodeId":"algo-1","Timestamp":1783653718.501992}
{"Type":"network","Name":"ReceiveBytesPerSecond","Dimension":"Algorithm","Value":0.00,"NodeId":"algo-1","Timestamp":1783653718.504715}
{"Type":"network","Name":"TransmitBytesPerSecond","Dimension":"Algorithm","Value":0.00,"NodeId":"algo-1","Timestamp":1783653718.504715}
{"Type":"network","Name":"ReceiveBytesPerSecond","Dimension":"Platform","Value":298508585.22,"NodeId":"algo-1","Timestamp":1783653718.504715}
{"Type":"network","Name":"TransmitBytesPerSecond","Dimension":"Platform","Value":462239.93,"NodeId":"algo-1","Timestamp":1783653718.504715}
{"Type":"gpu","Name":"gpu0","Dimension":"GPUUtilization","Value":0.00,"NodeId":"algo-1","Timestamp":1783653719.001150}
{"Type":"gpu","Name":"gpu0","Dimension":"GPUMemoryUtilization","Value":0.00,"NodeId":"algo-1","Timestamp":1783653719.001150}
{"Type":"cpu","Name":"cpu0","Dimension":"CPUUtilization","Value":78.72,"NodeId":"algo-1","Timestamp":1783653719.001202}
{"Type":"cpu","Name":"cpu0","Dimension":"I/OWaitPercentage","Value":31.91,"NodeId":"algo-1","Timestamp":1783653719.001202}
{"Type":"cpu","Name":"cpu1","Dimension":"CPUUtilization","Value":90.20,"NodeId":"algo-1","Timestamp":1783653719.001202}
{"Type":"cpu","Name":"cpu1","Dimension":"I/OWaitPercentage","Value":27.45,"NodeId":"algo-1","Timestamp":1783653719.001202}
{"Type":"cpu","Name":"cpu2","Dimension":"CPUUtilization","Value":87.50,"NodeId":"algo-1","Timestamp":1783653719.001202}
{"Type":"cpu","Name":"cpu2","Dimension":"I/OWaitPercentage","Value":33.33,"NodeId":"algo-1","Timestamp":1783653719.001202}
{"Type":"cpu","Name":"cpu3","Dimension":"CPUUtilization","Value":84.00,"NodeId":"algo-1","Timestamp":1783653719.001202}
{"Type":"cpu","Name":"cpu3","Dimension":"I/OWaitPercentage","Value":20.00,"NodeId":"algo-1","Timestamp":1783653719.001202}
{"Type":"i/o","Name":"IOPS","Dimension":"","Value":13751.30,"NodeId":"algo-1","Timestamp":1783653719.001296}
{"Type":"i/o","Name":"ReadThroughputInBytesPerSecond","Dimension":"","Value":0.00,"NodeId":"algo-1","Timestamp":1783653719.001296}
{"Type":"i/o","Name":"WriteThroughputInBytesPerSecond","Dimension":"","Value":1795209516.74,"NodeId":"algo-1","Timestamp":1783653719.001296}
{"Type":"memory","Name":"MemoryUsedPercent","Dimension":"","Value":10.42,"NodeId":"algo-1","Timestamp":1783653719.001621}
{"Type":"network","Name":"ReceiveBytesPerSecond","Dimension":"Algorithm","Value":0.00,"NodeId":"algo-1","Timestamp":1783653719.004158}
{"Type":"network","Name":"TransmitBytesPerSecond","Dimension":"Algorithm","Value":0.00,"NodeId":"algo-1","Timestamp":1783653719.004158}
{"Type":"network","Name":"ReceiveBytesPerSecond","Dimension":"Platform","Value":327548281.28,"NodeId":"algo-1","Timestamp":1783653719.004158}
{"Type":"network","Name":"TransmitBytesPerSecond","Dimension":"Platform","Value":405992.23,"NodeId":"algo-1","Timestamp":1783653719.004158}
{"Type":"gpu","Name":"gpu0","Dimension":"GPUUtilization","Value":0.00,"NodeId":"algo-1","Timestamp":1783653719.501572}
{"Type":"gpu","Name":"gpu0","Dimension":"GPUMemoryUtilization","Value":0.00,"NodeId":"algo-1","Timestamp":1783653719.501572}
{"Type":"i/o","Name":"IOPS","Dimension":"","Value":75798.23,"NodeId":"algo-1","Timestamp":1783653719.501585}
{"Type":"i/o","Name":"ReadThroughputInBytesPerSecond","Dimension":"","Value":11560428.43,"NodeId":"algo-1","Timestamp":1783653719.501585}
{"Type":"i/o","Name":"WriteThroughputInBytesPerSecond","Dimension":"","Value":6098991802.41,"NodeId":"algo-1","Timestamp":1783653719.501585}
{"Type":"cpu","Name":"cpu0","Dimension":"CPUUtilization","Value":70.00,"NodeId":"algo-1","Timestamp":1783653719.501617}
{"Type":"cpu","Name":"cpu0","Dimension":"I/OWaitPercentage","Value":24.00,"NodeId":"algo-1","Timestamp":1783653719.501617}
{"Type":"cpu","Name":"cpu1","Dimension":"CPUUtilization","Value":91.67,"NodeId":"algo-1","Timestamp":1783653719.501617}
{"Type":"cpu","Name":"cpu1","Dimension":"I/OWaitPercentage","Value":47.92,"NodeId":"algo-1","Timestamp":1783653719.501617}
{"Type":"cpu","Name":"cpu2","Dimension":"CPUUtilization","Value":82.35,"NodeId":"algo-1","Timestamp":1783653719.501617}
{"Type":"cpu","Name":"cpu2","Dimension":"I/OWaitPercentage","Value":11.76,"NodeId":"algo-1","Timestamp":1783653719.501617}
{"Type":"cpu","Name":"cpu3","Dimension":"CPUUtilization","Value":80.43,"NodeId":"algo-1","Timestamp":1783653719.501617}
{"Type":"cpu","Name":"cpu3","Dimension":"I/OWaitPercentage","Value":32.61,"NodeId":"algo-1","Timestamp":1783653719.501617}
{"Type":"memory","Name":"MemoryUsedPercent","Dimension":"","Value":10.43,"NodeId":"algo-1","Timestamp":1783653719.501663}
{"Type":"network","Name":"ReceiveBytesPerSecond","Dimension":"Algorithm","Value":0.00,"NodeId":"algo-1","Timestamp":1783653719.504054}
{"Type":"network","Name":"TransmitBytesPerSecond","Dimension":"Algorithm","Value":0.00,"NodeId":"algo-1","Timestamp":1783653719.504054}
{"Type":"network","Name":"ReceiveBytesPerSecond","Dimension":"Platform","Value":286849230.68,"NodeId":"algo-1","Timestamp":1783653719.504054}
{"Type":"network","Name":"TransmitBytesPerSecond","Dimension":"Platform","Value":366219.79,"NodeId":"algo-1","Timestamp":1783653719.504054}
